LICENSE.txt
MANIFEST.in
README.md
long_desc.txt
setup.cfg
setup.py
easy_dict/__init__.py
easy_dict.egg-info/PKG-INFO
easy_dict.egg-info/SOURCES.txt
easy_dict.egg-info/dependency_links.txt
easy_dict.egg-info/top_level.txt
easy_dict/tests/__init__.py
easy_dict/tests/test_01_default.py
easy_dict/tests/test_02_anchor.py
easy_dict/tests/test_03_gets.py
easy_dict/tests/test_04_mods.py
easy_dict/tests/test_05_sets.py