Metadata-Version: 1.1
Name: easy-dict
Version: 0.1.1
Summary: Easier way of accessing & assigning information in a nested dictionary.
Home-page: https://github.com/cahoy/NestedDictionary
Author: Cahyo Primawidodo
Author-email: cahyo.p@gmail.com
License: MIT
Keywords: easy simple nested flat default dictionary
Platform: UNKNOWN
Classifier: Intended Audience :: Developers
Classifier: Intended Audience :: Education
Classifier: Intended Audience :: Financial and Insurance Industry
Classifier: Intended Audience :: Information Technology
Classifier: Intended Audience :: Other Audience
Classifier: Intended Audience :: Science/Research
Classifier: License :: OSI Approved :: MIT License
Classifier: Programming Language :: Python :: 3.3
Classifier: Programming Language :: Python :: 3.4
Classifier: Programming Language :: Python :: 3.5
